netbox_prometheus_sd/__init__.py
netbox_prometheus_sd/settings.py
netbox_prometheus_sd/api/__init__.py
netbox_prometheus_sd/api/serializers.py
netbox_prometheus_sd/api/urls.py
netbox_prometheus_sd/api/utils.py
netbox_prometheus_sd/api/views.py
netbox_prometheus_sd-0.5.dist-info/LICENSE
netbox_prometheus_sd-0.5.dist-info/METADATA
netbox_prometheus_sd-0.5.dist-info/WHEEL
netbox_prometheus_sd-0.5.dist-info/top_level.txt
netbox_prometheus_sd-0.5.dist-info/RECORD
